gtime/__init__.py
gtime/_version.py
gtime/base.py
gtime/causality/__init__.py
gtime/causality/base.py
gtime/causality/granger_causality.py
gtime/causality/linear_coefficient.py
gtime/causality/pearson_correlation.py
gtime/causality/tests/__init__.py
gtime/causality/tests/common.py
gtime/causality/tests/test_granger_causality.py
gtime/causality/tests/test_linear_coefficient.py
gtime/causality/tests/test_pearson_correlation.py
gtime/compose/__init__.py
gtime/compose/feature_creation.py
gtime/experimental/__init__.py
gtime/explainability/__init__.py
gtime/explainability/explainer.py
gtime/explainability/tests/__init__.py
gtime/explainability/tests/test_explainer.py
gtime/external/__init__.py
gtime/external/hdays.py
gtime/external/make_holidays.py
gtime/feature_extraction/__init__.py
gtime/feature_extraction/custom.py
gtime/feature_extraction/standard.py
gtime/feature_extraction/trend.py
gtime/feature_extraction/tests/__init__.py
gtime/feature_extraction/tests/test_crest_factor_detrending.py
gtime/feature_extraction/tests/test_sorted_density.py
gtime/feature_extraction/tests/test_standard.py
gtime/feature_extraction/tests/test_trend.py
gtime/feature_generation/__init__.py
gtime/feature_generation/calendar.py
gtime/feature_generation/external.py
gtime/feature_generation/tests/__init__.py
gtime/feature_generation/tests/test_calendar.py
gtime/feature_generation/tests/test_external.py
gtime/forecasting/__init__.py
gtime/forecasting/gar.py
gtime/forecasting/naive.py
gtime/forecasting/online.py
gtime/forecasting/trend.py
gtime/forecasting/tests/__init__.py
gtime/forecasting/tests/test_gar.py
gtime/forecasting/tests/test_naive.py
gtime/forecasting/tests/test_online.py
gtime/forecasting/tests/test_trend.py
gtime/hierarchical/__init__.py
gtime/hierarchical/base.py
gtime/hierarchical/bottom_up.py
gtime/hierarchical/middle_out.py
gtime/hierarchical/naive.py
gtime/hierarchical/top_down.py
gtime/hierarchical/tests/__init__.py
gtime/hierarchical/tests/test_bottom_up.py
giotto_time-0.2.2.dist-info/LICENSE
giotto_time-0.2.2.dist-info/METADATA
giotto_time-0.2.2.dist-info/WHEEL
giotto_time-0.2.2.dist-info/top_level.txt
giotto_time-0.2.2.dist-info/RECORD
