Metadata-Version: 2.1
Name: giotto-time
Version: 0.2.2
Summary: Toolbox for Time Series analysis and integration with Machine Learning.
Home-page: https://github.com/giotto-ai/giotto-time
Download-URL: https://github.com/giotto-ai/giotto-time/tarball/v0.0a0
Maintainer: Alessio Baccelli
Maintainer-email: maintainers@giotto.ai
License: AGPLv3
Keywords: machine learning time series data analysis topology,persistence diagrams
Classifier: Intended Audience :: Information Technology
Classifier: Intended Audience :: Developers
Classifier: License :: OSI Approved
Classifier: Programming Language :: Python
Classifier: Topic :: Software Development
Classifier: Topic :: Scientific/Engineering
Classifier: Operating System :: Microsoft :: Windows
Classifier: Operating System :: POSIX
Classifier: Operating System :: Unix
Classifier: Operating System :: MacOS
Classifier: Programming Language :: Python :: 3.7
Classifier: Programming Language :: Python :: 3.8
Classifier: Programming Language :: Python :: 3.9
License-File: LICENSE
Requires-Dist: pandas (>=0.25.3)
Requires-Dist: scipy (>=0.17.0)
Requires-Dist: scikit-learn (>=0.22.0)
Requires-Dist: matplotlib (>=3.1.0)
Requires-Dist: lime (>=0.2.0.0)
Requires-Dist: shap (>=0.35)
Requires-Dist: holidays (>=0.10.2)
Requires-Dist: lunarcalendar (>=0.0.9)
Requires-Dist: giotto-tda
Provides-Extra: doc
Requires-Dist: sphinx ; extra == 'doc'
Requires-Dist: numpydoc ; extra == 'doc'
Requires-Dist: sphinx-issues ; extra == 'doc'
Requires-Dist: sphinx-rtd-theme ; extra == 'doc'
Provides-Extra: examples
Provides-Extra: tests
Requires-Dist: hypothesis (==5.5.3) ; extra == 'tests'
Requires-Dist: black ; extra == 'tests'
Requires-Dist: pre-commit ; extra == 'tests'
Requires-Dist: pytest ; extra == 'tests'
Requires-Dist: pytest-cov ; extra == 'tests'
Requires-Dist: pytest-xdist ; extra == 'tests'
Requires-Dist: pytest-lazy-fixture ; extra == 'tests'
Requires-Dist: flake8 ; extra == 'tests'
Requires-Dist: mypy ; extra == 'tests'
Requires-Dist: nbconvert ; extra == 'tests'
Requires-Dist: jupyter ; extra == 'tests'
